testcontainers/kafka/__init__.py
tests/test_kafka.py
testcontainers_kafka-0.0.1rc1.dist-info/METADATA
testcontainers_kafka-0.0.1rc1.dist-info/WHEEL
testcontainers_kafka-0.0.1rc1.dist-info/top_level.txt
testcontainers_kafka-0.0.1rc1.dist-info/RECORD
